{
    "schemes": [
        "http",
        "https"
    ],
    "swagger": "2.0",
    "info": {
        "description": "REST API for Computer Peripherals Store (MongoDB + Gin)",
        "title": "Peripherals Store API",
        "contact": {},
        "version": "1.0"
    },
    "host": "localhost:8080",
    "basePath": "/api/v1",
    "paths": {
        "/admin/auth/admin/register": {
            "post": {
                "description": "Create new account and return JWT token",
                "consumes": [
                    "application/json"
                ],
                "produces": [
                    "application/json"
                ],
                "tags": [
                    "Auth"
                ],
                "summary": "Register new admin",
                "parameters": [
                    {
                        "description": "Register data",
                        "name": "body",
                        "in": "body",
                        "required": true,
                        "schema": {
                            "$ref": "#/definitions/handlers.RegisterRequest"
                        }
                    }
                ],
                "responses": {
                    "201": {
                        "description": "Created",
                        "schema": {
                            "type": "object",
                            "additionalProperties": true
                        }
                    },
                    "400": {
                        "description": "Bad Request",
                        "schema": {
                            "type": "object",
                            "additionalProperties": {
                                "type": "string"
                            }
                        }
                    },
                    "409": {
                        "description": "Conflict",
                        "schema": {
                            "type": "object",
                            "additionalProperties": {
                                "type": "string"
                            }
                        }
                    },
                    "500": {
                        "description": "Internal Server Error",
                        "schema": {
                            "type": "object",
                            "additionalProperties": {
                                "type": "string"
                            }
                        }
                    }
                }
            }
        },
        "/admin/categories": {
            "post": {
                "consumes": [
                    "application/json"
                ],
                "produces": [
                    "application/json"
                ],
                "tags": [
                    "Admin Categories"
                ],
                "summary": "Create category",
                "parameters": [
                    {
                        "description": "Category",
                        "name": "body",
                        "in": "body",
                        "required": true,
                        "schema": {
                            "$ref": "#/definitions/handlers.CreateCategoryRequest"
                        }
                    }
                ],
                "responses": {
                    "201": {
                        "description": "Created",
                        "schema": {
                            "type": "object",
                            "additionalProperties": true
                        }
                    },
                    "400": {
                        "description": "Bad Request",
                        "schema": {
                            "type": "object",
                            "additionalProperties": {
                                "type": "string"
                            }
                        }
                    }
                }
            }
        },
        "/admin/categories/{id}": {
            "put": {
                "consumes": [
                    "application/json"
                ],
                "produces": [
                    "application/json"
                ],
                "tags": [
                    "Admin Categories"
                ],
                "summary": "Update category",
                "parameters": [
                    {
                        "type": "string",
                        "description": "Category ID",
                        "name": "id",
                        "in": "path",
                        "required": true
                    },
                    {
                        "description": "Patch",
                        "name": "body",
                        "in": "body",
                        "required": true,
                        "schema": {
                            "$ref": "#/definitions/handlers.UpdateCategoryRequest"
                        }
                    }
                ],
                "responses": {
                    "200": {
                        "description": "OK",
                        "schema": {
                            "type": "object",
                            "additionalProperties": true
                        }
                    },
                    "400": {
                        "description": "Bad Request",
                        "schema": {
                            "type": "object",
                            "additionalProperties": {
                                "type": "string"
                            }
                        }
                    },
                    "404": {
                        "description": "Not Found",
                        "schema": {
                            "type": "object",
                            "additionalProperties": {
                                "type": "string"
                            }
                        }
                    }
                }
            },
            "delete": {
                "produces": [
                    "application/json"
                ],
                "tags": [
                    "Admin Categories"
                ],
                "summary": "Delete category",
                "parameters": [
                    {
                        "type": "string",
                        "description": "Category ID",
                        "name": "id",
                        "in": "path",
                        "required": true
                    }
                ],
                "responses": {
                    "204": {
                        "description": "No Content"
                    },
                    "400": {
                        "description": "Bad Request",
                        "schema": {
                            "type": "object",
                            "additionalProperties": {
                                "type": "string"
                            }
                        }
                    },
                    "404": {
                        "description": "Not Found",
                        "schema": {
                            "type": "object",
                            "additionalProperties": {
                                "type": "string"
                            }
                        }
                    },
                    "409": {
                        "description": "Conflict",
                        "schema": {
                            "type": "object",
                            "additionalProperties": {
                                "type": "string"
                            }
                        }
                    }
                }
            }
        },
        "/admin/orders/{id}/status": {
            "put": {
                "consumes": [
                    "application/json"
                ],
                "produces": [
                    "application/json"
                ],
                "tags": [
                    "Admin Orders"
                ],
                "summary": "Update order status (admin only)",
                "parameters": [
                    {
                        "type": "string",
                        "description": "Order ID",
                        "name": "id",
                        "in": "path",
                        "required": true
                    },
                    {
                        "description": "Status",
                        "name": "body",
                        "in": "body",
                        "required": true,
                        "schema": {
                            "$ref": "#/definitions/handlers.UpdateOrderStatusRequest"
                        }
                    }
                ],
                "responses": {
                    "200": {
                        "description": "OK",
                        "schema": {
                            "type": "object",
                            "additionalProperties": true
                        }
                    },
                    "400": {
                        "description": "Bad Request",
                        "schema": {
                            "type": "object",
                            "additionalProperties": {
                                "type": "string"
                            }
                        }
                    },
                    "401": {
                        "description": "Unauthorized",
                        "schema": {
                            "type": "object",
                            "additionalProperties": {
                                "type": "string"
                            }
                        }
                    },
                    "403": {
                        "description": "Forbidden",
                        "schema": {
                            "type": "object",
                            "additionalProperties": {
                                "type": "string"
                            }
                        }
                    },
                    "404": {
                        "description": "Not Found",
                        "schema": {
                            "type": "object",
                            "additionalProperties": {
                                "type": "string"
                            }
                        }
                    }
                }
            }
        },
        "/admin/products": {
            "post": {
                "consumes": [
                    "application/json"
                ],
                "produces": [
                    "application/json"
                ],
                "tags": [
                    "Admin Products"
                ],
                "summary": "Create product",
                "parameters": [
                    {
                        "description": "Product",
                        "name": "body",
                        "in": "body",
                        "required": true,
                        "schema": {
                            "$ref": "#/definitions/handlers.CreateProductRequest"
                        }
                    }
                ],
                "responses": {
                    "201": {
                        "description": "Created",
                        "schema": {
                            "type": "object",
                            "additionalProperties": true
                        }
                    },
                    "400": {
                        "description": "Bad Request",
                        "schema": {
                            "type": "object",
                            "additionalProperties": {
                                "type": "string"
                            }
                        }
                    }
                }
            }
        },
        "/admin/products/{id}": {
            "put": {
                "consumes": [
                    "application/json"
                ],
                "produces": [
                    "application/json"
                ],
                "tags": [
                    "Admin Products"
                ],
                "summary": "Update product",
                "parameters": [
                    {
                        "type": "string",
                        "description": "Product ID",
                        "name": "id",
                        "in": "path",
                        "required": true
                    },
                    {
                        "description": "Patch",
                        "name": "body",
                        "in": "body",
                        "required": true,
                        "schema": {
                            "$ref": "#/definitions/handlers.UpdateProductRequest"
                        }
                    }
                ],
                "responses": {
                    "200": {
                        "description": "OK",
                        "schema": {
                            "type": "object",
                            "additionalProperties": true
                        }
                    },
                    "400": {
                        "description": "Bad Request",
                        "schema": {
                            "type": "object",
                            "additionalProperties": {
                                "type": "string"
                            }
                        }
                    },
                    "404": {
                        "description": "Not Found",
                        "schema": {
                            "type": "object",
                            "additionalProperties": {
                                "type": "string"
                            }
                        }
                    }
                }
            },
            "delete": {
                "produces": [
                    "application/json"
                ],
                "tags": [
                    "Admin Products"
                ],
                "summary": "Delete product",
                "parameters": [
                    {
                        "type": "string",
                        "description": "Product ID",
                        "name": "id",
                        "in": "path",
                        "required": true
                    }
                ],
                "responses": {
                    "204": {
                        "description": "No Content"
                    },
                    "400": {
                        "description": "Bad Request",
                        "schema": {
                            "type": "object",
                            "additionalProperties": {
                                "type": "string"
                            }
                        }
                    },
                    "404": {
                        "description": "Not Found",
                        "schema": {
                            "type": "object",
                            "additionalProperties": {
                                "type": "string"
                            }
                        }
                    }
                }
            }
        },
        "/admin/statistics/products": {
            "get": {
                "produces": [
                    "application/json"
                ],
                "tags": [
                    "Admin Statistics"
                ],
                "summary": "Get all products statistics (admin only)",
                "responses": {
                    "200": {
                        "description": "OK",
                        "schema": {
                            "$ref": "#/definitions/statistics.ProductStatistics"
                        }
                    },
                    "401": {
                        "description": "Unauthorized",
                        "schema": {
                            "type": "object",
                            "additionalProperties": {
                                "type": "string"
                            }
                        }
                    },
                    "403": {
                        "description": "Forbidden",
                        "schema": {
                            "type": "object",
                            "additionalProperties": {
                                "type": "string"
                            }
                        }
                    }
                }
            }
        },
        "/admin/statistics/products/date-range": {
            "post": {
                "consumes": [
                    "application/json"
                ],
                "produces": [
                    "application/json"
                ],
                "tags": [
                    "Admin Statistics"
                ],
                "summary": "Get products statistics by date range (admin only)",
                "parameters": [
                    {
                        "description": "Date Range",
                        "name": "body",
                        "in": "body",
                        "required": true,
                        "schema": {
                            "$ref": "#/definitions/handlers.DateRangeRequest"
                        }
                    }
                ],
                "responses": {
                    "200": {
                        "description": "OK",
                        "schema": {
                            "$ref": "#/definitions/statistics.ProductStatistics"
                        }
                    },
                    "400": {
                        "description": "Bad Request",
                        "schema": {
                            "type": "object",
                            "additionalProperties": {
                                "type": "string"
                            }
                        }
                    },
                    "401": {
                        "description": "Unauthorized",
                        "schema": {
                            "type": "object",
                            "additionalProperties": {
                                "type": "string"
                            }
                        }
                    },
                    "403": {
                        "description": "Forbidden",
                        "schema": {
                            "type": "object",
                            "additionalProperties": {
                                "type": "string"
                            }
                        }
                    }
                }
            }
        },
        "/admin/statistics/products/year": {
            "post": {
                "consumes": [
                    "application/json"
                ],
                "produces": [
                    "application/json"
                ],
                "tags": [
                    "Admin Statistics"
                ],
                "summary": "Get products statistics by year (admin only)",
                "parameters": [
                    {
                        "description": "Year",
                        "name": "body",
                        "in": "body",
                        "required": true,
                        "schema": {
                            "$ref": "#/definitions/handlers.YearRequest"
                        }
                    }
                ],
                "responses": {
                    "200": {
                        "description": "OK",
                        "schema": {
                            "$ref": "#/definitions/statistics.ProductStatistics"
                        }
                    },
                    "400": {
                        "description": "Bad Request",
                        "schema": {
                            "type": "object",
                            "additionalProperties": {
                                "type": "string"
                            }
                        }
                    },
                    "401": {
                        "description": "Unauthorized",
                        "schema": {
                            "type": "object",
                            "additionalProperties": {
                                "type": "string"
                            }
                        }
                    },
                    "403": {
                        "description": "Forbidden",
                        "schema": {
                            "type": "object",
                            "additionalProperties": {
                                "type": "string"
                            }
                        }
                    }
                }
            }
        },
        "/admin/statistics/sales": {
            "get": {
                "produces": [
                    "application/json"
                ],
                "tags": [
                    "Admin Statistics"
                ],
                "summary": "Get all sales statistics (admin only)",
                "responses": {
                    "200": {
                        "description": "OK",
                        "schema": {
                            "$ref": "#/definitions/statistics.SalesStatistics"
                        }
                    },
                    "401": {
                        "description": "Unauthorized",
                        "schema": {
                            "type": "object",
                            "additionalProperties": {
                                "type": "string"
                            }
                        }
                    },
                    "403": {
                        "description": "Forbidden",
                        "schema": {
                            "type": "object",
                            "additionalProperties": {
                                "type": "string"
                            }
                        }
                    }
                }
            }
        },
        "/admin/statistics/sales/date-range": {
            "post": {
                "consumes": [
                    "application/json"
                ],
                "produces": [
                    "application/json"
                ],
                "tags": [
                    "Admin Statistics"
                ],
                "summary": "Get sales statistics by date range (admin only)",
                "parameters": [
                    {
                        "description": "Date Range",
                        "name": "body",
                        "in": "body",
                        "required": true,
                        "schema": {
                            "$ref": "#/definitions/handlers.DateRangeRequest"
                        }
                    }
                ],
                "responses": {
                    "200": {
                        "description": "OK",
                        "schema": {
                            "$ref": "#/definitions/statistics.SalesStatistics"
                        }
                    },
                    "400": {
                        "description": "Bad Request",
                        "schema": {
                            "type": "object",
                            "additionalProperties": {
                                "type": "string"
                            }
                        }
                    },
                    "401": {
                        "description": "Unauthorized",
                        "schema": {
                            "type": "object",
                            "additionalProperties": {
                                "type": "string"
                            }
                        }
                    },
                    "403": {
                        "description": "Forbidden",
                        "schema": {
                            "type": "object",
                            "additionalProperties": {
                                "type": "string"
                            }
                        }
                    }
                }
            }
        },
        "/admin/statistics/sales/year": {
            "post": {
                "consumes": [
                    "application/json"
                ],
                "produces": [
                    "application/json"
                ],
                "tags": [
                    "Admin Statistics"
                ],
                "summary": "Get sales statistics by year (admin only)",
                "parameters": [
                    {
                        "description": "Year",
                        "name": "body",
                        "in": "body",
                        "required": true,
                        "schema": {
                            "$ref": "#/definitions/handlers.YearRequest"
                        }
                    }
                ],
                "responses": {
                    "200": {
                        "description": "OK",
                        "schema": {
                            "$ref": "#/definitions/statistics.SalesStatistics"
                        }
                    },
                    "400": {
                        "description": "Bad Request",
                        "schema": {
                            "type": "object",
                            "additionalProperties": {
                                "type": "string"
                            }
                        }
                    },
                    "401": {
                        "description": "Unauthorized",
                        "schema": {
                            "type": "object",
                            "additionalProperties": {
                                "type": "string"
                            }
                        }
                    },
                    "403": {
                        "description": "Forbidden",
                        "schema": {
                            "type": "object",
                            "additionalProperties": {
                                "type": "string"
                            }
                        }
                    }
                }
            }
        },
        "/auth/login": {
            "post": {
                "description": "Authenticate user and return JWT token",
                "consumes": [
                    "application/json"
                ],
                "produces": [
                    "application/json"
                ],
                "tags": [
                    "Auth"
                ],
                "summary": "Login user",
                "parameters": [
                    {
                        "description": "Login data",
                        "name": "body",
                        "in": "body",
                        "required": true,
                        "schema": {
                            "$ref": "#/definitions/handlers.LoginRequest"
                        }
                    }
                ],
                "responses": {
                    "200": {
                        "description": "OK",
                        "schema": {
                            "type": "object",
                            "additionalProperties": true
                        }
                    },
                    "400": {
                        "description": "Bad Request",
                        "schema": {
                            "type": "object",
                            "additionalProperties": {
                                "type": "string"
                            }
                        }
                    },
                    "401": {
                        "description": "Unauthorized",
                        "schema": {
                            "type": "object",
                            "additionalProperties": {
                                "type": "string"
                            }
                        }
                    },
                    "500": {
                        "description": "Internal Server Error",
                        "schema": {
                            "type": "object",
                            "additionalProperties": {
                                "type": "string"
                            }
                        }
                    }
                }
            }
        },
        "/auth/register": {
            "post": {
                "description": "Create new account and return JWT token",
                "consumes": [
                    "application/json"
                ],
                "produces": [
                    "application/json"
                ],
                "tags": [
                    "Auth"
                ],
                "summary": "Register new user",
                "parameters": [
                    {
                        "description": "Register data",
                        "name": "body",
                        "in": "body",
                        "required": true,
                        "schema": {
                            "$ref": "#/definitions/handlers.RegisterRequest"
                        }
                    }
                ],
                "responses": {
                    "201": {
                        "description": "Created",
                        "schema": {
                            "type": "object",
                            "additionalProperties": true
                        }
                    },
                    "400": {
                        "description": "Bad Request",
                        "schema": {
                            "type": "object",
                            "additionalProperties": {
                                "type": "string"
                            }
                        }
                    },
                    "409": {
                        "description": "Conflict",
                        "schema": {
                            "type": "object",
                            "additionalProperties": {
                                "type": "string"
                            }
                        }
                    },
                    "500": {
                        "description": "Internal Server Error",
                        "schema": {
                            "type": "object",
                            "additionalProperties": {
                                "type": "string"
                            }
                        }
                    }
                }
            }
        },
        "/categories": {
            "get": {
                "produces": [
                    "application/json"
                ],
                "tags": [
                    "Categories"
                ],
                "summary": "List categories",
                "parameters": [
                    {
                        "type": "integer",
                        "description": "Offset for pagination",
                        "name": "offset",
                        "in": "query",
                        "required": true
                    },
                    {
                        "type": "integer",
                        "description": "Limit for pagination",
                        "name": "limit",
                        "in": "query",
                        "required": true
                    }
                ],
                "responses": {
                    "200": {
                        "description": "OK",
                        "schema": {
                            "type": "array",
                            "items": {
                                "type": "object",
                                "additionalProperties": true
                            }
                        }
                    },
                    "400": {
                        "description": "Bad Request",
                        "schema": {
                            "type": "object",
                            "additionalProperties": {
                                "type": "string"
                            }
                        }
                    }
                }
            }
        },
        "/categories/{id}": {
            "get": {
                "produces": [
                    "application/json"
                ],
                "tags": [
                    "Categories"
                ],
                "summary": "Get category by ID",
                "parameters": [
                    {
                        "type": "string",
                        "description": "Category ID",
                        "name": "id",
                        "in": "path",
                        "required": true
                    }
                ],
                "responses": {
                    "200": {
                        "description": "OK",
                        "schema": {
                            "type": "object",
                            "additionalProperties": true
                        }
                    },
                    "400": {
                        "description": "Bad Request",
                        "schema": {
                            "type": "object",
                            "additionalProperties": {
                                "type": "string"
                            }
                        }
                    },
                    "404": {
                        "description": "Not Found",
                        "schema": {
                            "type": "object",
                            "additionalProperties": {
                                "type": "string"
                            }
                        }
                    }
                }
            }
        },
        "/orders": {
            "get": {
                "produces": [
                    "application/json"
                ],
                "tags": [
                    "Orders"
                ],
                "summary": "List orders (user: own, admin: all)",
                "parameters": [
                    {
                        "type": "integer",
                        "description": "Offset for pagination",
                        "name": "offset",
                        "in": "query",
                        "required": true
                    },
                    {
                        "type": "integer",
                        "description": "Limit for pagination",
                        "name": "limit",
                        "in": "query",
                        "required": true
                    }
                ],
                "responses": {
                    "200": {
                        "description": "OK",
                        "schema": {
                            "type": "array",
                            "items": {
                                "type": "object",
                                "additionalProperties": true
                            }
                        }
                    },
                    "400": {
                        "description": "Bad Request",
                        "schema": {
                            "type": "object",
                            "additionalProperties": {
                                "type": "string"
                            }
                        }
                    },
                    "401": {
                        "description": "Unauthorized",
                        "schema": {
                            "type": "object",
                            "additionalProperties": {
                                "type": "string"
                            }
                        }
                    }
                }
            },
            "post": {
                "consumes": [
                    "application/json"
                ],
                "produces": [
                    "application/json"
                ],
                "tags": [
                    "Orders"
                ],
                "summary": "Create order (auth required)",
                "parameters": [
                    {
                        "description": "Order",
                        "name": "body",
                        "in": "body",
                        "required": true,
                        "schema": {
                            "$ref": "#/definitions/handlers.CreateOrderRequest"
                        }
                    }
                ],
                "responses": {
                    "201": {
                        "description": "Created",
                        "schema": {
                            "type": "object",
                            "additionalProperties": true
                        }
                    },
                    "400": {
                        "description": "Bad Request",
                        "schema": {
                            "type": "object",
                            "additionalProperties": {
                                "type": "string"
                            }
                        }
                    },
                    "401": {
                        "description": "Unauthorized",
                        "schema": {
                            "type": "object",
                            "additionalProperties": {
                                "type": "string"
                            }
                        }
                    }
                }
            }
        },
        "/orders/{id}": {
            "get": {
                "produces": [
                    "application/json"
                ],
                "tags": [
                    "Orders"
                ],
                "summary": "Get order by ID (user: own, admin: any)",
                "parameters": [
                    {
                        "type": "string",
                        "description": "Order ID",
                        "name": "id",
                        "in": "path",
                        "required": true
                    }
                ],
                "responses": {
                    "200": {
                        "description": "OK",
                        "schema": {
                            "type": "object",
                            "additionalProperties": true
                        }
                    },
                    "400": {
                        "description": "Bad Request",
                        "schema": {
                            "type": "object",
                            "additionalProperties": {
                                "type": "string"
                            }
                        }
                    },
                    "401": {
                        "description": "Unauthorized",
                        "schema": {
                            "type": "object",
                            "additionalProperties": {
                                "type": "string"
                            }
                        }
                    },
                    "404": {
                        "description": "Not Found",
                        "schema": {
                            "type": "object",
                            "additionalProperties": {
                                "type": "string"
                            }
                        }
                    }
                }
            }
        },
        "/products": {
            "get": {
                "produces": [
                    "application/json"
                ],
                "tags": [
                    "Products"
                ],
                "summary": "List products",
                "parameters": [
                    {
                        "type": "string",
                        "description": "Category ID (ObjectId hex)",
                        "name": "categoryId",
                        "in": "query"
                    },
                    {
                        "type": "integer",
                        "description": "Offset for pagination",
                        "name": "offset",
                        "in": "query",
                        "required": true
                    },
                    {
                        "type": "integer",
                        "description": "Limit for pagination",
                        "name": "limit",
                        "in": "query",
                        "required": true
                    }
                ],
                "responses": {
                    "200": {
                        "description": "OK",
                        "schema": {
                            "type": "array",
                            "items": {
                                "type": "object",
                                "additionalProperties": true
                            }
                        }
                    },
                    "400": {
                        "description": "Bad Request",
                        "schema": {
                            "type": "object",
                            "additionalProperties": {
                                "type": "string"
                            }
                        }
                    }
                }
            }
        },
        "/products/{id}": {
            "get": {
                "produces": [
                    "application/json"
                ],
                "tags": [
                    "Products"
                ],
                "summary": "Get product by ID",
                "parameters": [
                    {
                        "type": "string",
                        "description": "Product ID",
                        "name": "id",
                        "in": "path",
                        "required": true
                    }
                ],
                "responses": {
                    "200": {
                        "description": "OK",
                        "schema": {
                            "type": "object",
                            "additionalProperties": true
                        }
                    },
                    "400": {
                        "description": "Bad Request",
                        "schema": {
                            "type": "object",
                            "additionalProperties": {
                                "type": "string"
                            }
                        }
                    },
                    "404": {
                        "description": "Not Found",
                        "schema": {
                            "type": "object",
                            "additionalProperties": {
                                "type": "string"
                            }
                        }
                    }
                }
            }
        },
        "/products/{id}/reviews": {
            "post": {
                "consumes": [
                    "application/json"
                ],
                "produces": [
                    "application/json"
                ],
                "tags": [
                    "Reviews"
                ],
                "summary": "Add product review (auth required)",
                "parameters": [
                    {
                        "type": "string",
                        "description": "Product ID",
                        "name": "id",
                        "in": "path",
                        "required": true
                    },
                    {
                        "description": "Review",
                        "name": "body",
                        "in": "body",
                        "required": true,
                        "schema": {
                            "$ref": "#/definitions/handlers.AddReviewRequest"
                        }
                    }
                ],
                "responses": {
                    "201": {
                        "description": "Created",
                        "schema": {
                            "type": "object",
                            "additionalProperties": true
                        }
                    },
                    "400": {
                        "description": "Bad Request",
                        "schema": {
                            "type": "object",
                            "additionalProperties": {
                                "type": "string"
                            }
                        }
                    },
                    "401": {
                        "description": "Unauthorized",
                        "schema": {
                            "type": "object",
                            "additionalProperties": {
                                "type": "string"
                            }
                        }
                    },
                    "404": {
                        "description": "Not Found",
                        "schema": {
                            "type": "object",
                            "additionalProperties": {
                                "type": "string"
                            }
                        }
                    }
                }
            }
        },
        "/products/{id}/reviews/{reviewId}": {
            "delete": {
                "produces": [
                    "application/json"
                ],
                "tags": [
                    "Reviews"
                ],
                "summary": "Delete product review (auth required)",
                "parameters": [
                    {
                        "type": "string",
                        "description": "Product ID",
                        "name": "id",
                        "in": "path",
                        "required": true
                    },
                    {
                        "type": "string",
                        "description": "Review ID",
                        "name": "reviewId",
                        "in": "path",
                        "required": true
                    }
                ],
                "responses": {
                    "204": {
                        "description": "No Content"
                    },
                    "400": {
                        "description": "Bad Request",
                        "schema": {
                            "type": "object",
                            "additionalProperties": {
                                "type": "string"
                            }
                        }
                    },
                    "401": {
                        "description": "Unauthorized",
                        "schema": {
                            "type": "object",
                            "additionalProperties": {
                                "type": "string"
                            }
                        }
                    },
                    "404": {
                        "description": "Not Found",
                        "schema": {
                            "type": "object",
                            "additionalProperties": {
                                "type": "string"
                            }
                        }
                    }
                }
            }
        },
        "/profile": {
            "get": {
                "produces": [
                    "application/json"
                ],
                "tags": [
                    "Profile"
                ],
                "summary": "Get user profile (auth required)",
                "responses": {
                    "200": {
                        "description": "OK",
                        "schema": {
                            "type": "object",
                            "additionalProperties": true
                        }
                    },
                    "401": {
                        "description": "Unauthorized",
                        "schema": {
                            "type": "object",
                            "additionalProperties": {
                                "type": "string"
                            }
                        }
                    },
                    "404": {
                        "description": "Not Found",
                        "schema": {
                            "type": "object",
                            "additionalProperties": {
                                "type": "string"
                            }
                        }
                    }
                }
            },
            "put": {
                "consumes": [
                    "application/json"
                ],
                "produces": [
                    "application/json"
                ],
                "tags": [
                    "Profile"
                ],
                "summary": "Update user profile (auth required)",
                "parameters": [
                    {
                        "description": "Profile data",
                        "name": "body",
                        "in": "body",
                        "required": true,
                        "schema": {
                            "$ref": "#/definitions/handlers.UpdateProfileRequest"
                        }
                    }
                ],
                "responses": {
                    "200": {
                        "description": "OK",
                        "schema": {
                            "type": "object",
                            "additionalProperties": true
                        }
                    },
                    "400": {
                        "description": "Bad Request",
                        "schema": {
                            "type": "object",
                            "additionalProperties": {
                                "type": "string"
                            }
                        }
                    },
                    "401": {
                        "description": "Unauthorized",
                        "schema": {
                            "type": "object",
                            "additionalProperties": {
                                "type": "string"
                            }
                        }
                    },
                    "404": {
                        "description": "Not Found",
                        "schema": {
                            "type": "object",
                            "additionalProperties": {
                                "type": "string"
                            }
                        }
                    }
                }
            }
        },
        "/wishlist": {
            "get": {
                "produces": [
                    "application/json"
                ],
                "tags": [
                    "Wishlist"
                ],
                "summary": "Get user's wishlist (auth required)",
                "parameters": [
                    {
                        "type": "integer",
                        "description": "Offset for pagination",
                        "name": "offset",
                        "in": "query",
                        "required": true
                    },
                    {
                        "type": "integer",
                        "description": "Limit for pagination",
                        "name": "limit",
                        "in": "query",
                        "required": true
                    }
                ],
                "responses": {
                    "200": {
                        "description": "OK",
                        "schema": {
                            "type": "array",
                            "items": {
                                "type": "object",
                                "additionalProperties": true
                            }
                        }
                    },
                    "400": {
                        "description": "Bad Request",
                        "schema": {
                            "type": "object",
                            "additionalProperties": {
                                "type": "string"
                            }
                        }
                    },
                    "401": {
                        "description": "Unauthorized",
                        "schema": {
                            "type": "object",
                            "additionalProperties": {
                                "type": "string"
                            }
                        }
                    }
                }
            },
            "post": {
                "consumes": [
                    "application/json"
                ],
                "produces": [
                    "application/json"
                ],
                "tags": [
                    "Wishlist"
                ],
                "summary": "Add product to wishlist (auth required)",
                "parameters": [
                    {
                        "description": "Product ID",
                        "name": "body",
                        "in": "body",
                        "required": true,
                        "schema": {
                            "$ref": "#/definitions/handlers.AddToWishlistRequest"
                        }
                    }
                ],
                "responses": {
                    "201": {
                        "description": "Created",
                        "schema": {
                            "type": "object",
                            "additionalProperties": true
                        }
                    },
                    "400": {
                        "description": "Bad Request",
                        "schema": {
                            "type": "object",
                            "additionalProperties": {
                                "type": "string"
                            }
                        }
                    },
                    "401": {
                        "description": "Unauthorized",
                        "schema": {
                            "type": "object",
                            "additionalProperties": {
                                "type": "string"
                            }
                        }
                    },
                    "409": {
                        "description": "Conflict",
                        "schema": {
                            "type": "object",
                            "additionalProperties": {
                                "type": "string"
                            }
                        }
                    }
                }
            }
        },
        "/wishlist/{id}": {
            "delete": {
                "produces": [
                    "application/json"
                ],
                "tags": [
                    "Wishlist"
                ],
                "summary": "Remove product from wishlist (auth required)",
                "parameters": [
                    {
                        "type": "string",
                        "description": "Wishlist Item ID",
                        "name": "id",
                        "in": "path",
                        "required": true
                    }
                ],
                "responses": {
                    "204": {
                        "description": "No Content"
                    },
                    "400": {
                        "description": "Bad Request",
                        "schema": {
                            "type": "object",
                            "additionalProperties": {
                                "type": "string"
                            }
                        }
                    },
                    "401": {
                        "description": "Unauthorized",
                        "schema": {
                            "type": "object",
                            "additionalProperties": {
                                "type": "string"
                            }
                        }
                    },
                    "404": {
                        "description": "Not Found",
                        "schema": {
                            "type": "object",
                            "additionalProperties": {
                                "type": "string"
                            }
                        }
                    }
                }
            }
        }
    },
    "definitions": {
        "handlers.AddReviewRequest": {
            "type": "object",
            "required": [
                "rating"
            ],
            "properties": {
                "comment": {
                    "type": "string"
                },
                "rating": {
                    "type": "integer"
                }
            }
        },
        "handlers.AddToWishlistRequest": {
            "type": "object",
            "required": [
                "product_id"
            ],
            "properties": {
                "product_id": {
                    "type": "string"
                }
            }
        },
        "handlers.CreateCategoryRequest": {
            "type": "object",
            "required": [
                "name"
            ],
            "properties": {
                "description": {
                    "type": "string"
                },
                "name": {
                    "type": "string"
                }
            }
        },
        "handlers.CreateOrderRequest": {
            "type": "object",
            "required": [
                "items"
            ],
            "properties": {
                "items": {
                    "type": "array",
                    "items": {
                        "type": "object",
                        "required": [
                            "productId",
                            "quantity"
                        ],
                        "properties": {
                            "productId": {
                                "type": "string"
                            },
                            "quantity": {
                                "type": "integer"
                            }
                        }
                    }
                }
            }
        },
        "handlers.CreateProductRequest": {
            "type": "object",
            "required": [
                "categoryId",
                "name",
                "price",
                "stock"
            ],
            "properties": {
                "categoryId": {
                    "type": "string"
                },
                "description": {
                    "type": "string"
                },
                "name": {
                    "type": "string"
                },
                "price": {
                    "type": "number"
                },
                "stock": {
                    "type": "integer"
                }
            }
        },
        "handlers.DateRangeRequest": {
            "type": "object",
            "required": [
                "end_date",
                "start_date"
            ],
            "properties": {
                "end_date": {
                    "type": "string"
                },
                "start_date": {
                    "type": "string"
                }
            }
        },
        "handlers.LoginRequest": {
            "type": "object",
            "required": [
                "email",
                "password"
            ],
            "properties": {
                "email": {
                    "type": "string"
                },
                "password": {
                    "type": "string"
                }
            }
        },
        "handlers.RegisterRequest": {
            "type": "object",
            "required": [
                "email",
                "name",
                "password"
            ],
            "properties": {
                "email": {
                    "type": "string"
                },
                "name": {
                    "type": "string",
                    "maxLength": 60,
                    "minLength": 2
                },
                "password": {
                    "type": "string",
                    "maxLength": 72,
                    "minLength": 6
                }
            }
        },
        "handlers.UpdateCategoryRequest": {
            "type": "object",
            "properties": {
                "description": {
                    "type": "string"
                },
                "name": {
                    "type": "string"
                }
            }
        },
        "handlers.UpdateOrderStatusRequest": {
            "type": "object",
            "required": [
                "status"
            ],
            "properties": {
                "status": {
                    "type": "string"
                }
            }
        },
        "handlers.UpdateProductRequest": {
            "type": "object",
            "properties": {
                "categoryId": {
                    "type": "string"
                },
                "description": {
                    "type": "string"
                },
                "name": {
                    "type": "string"
                },
                "price": {
                    "type": "number"
                },
                "stock": {
                    "type": "integer"
                }
            }
        },
        "handlers.UpdateProfileRequest": {
            "type": "object",
            "properties": {
                "address": {
                    "type": "string"
                },
                "bio": {
                    "type": "string"
                },
                "name": {
                    "type": "string"
                },
                "phone": {
                    "type": "string"
                }
            }
        },
        "handlers.YearRequest": {
            "type": "object",
            "required": [
                "year"
            ],
            "properties": {
                "year": {
                    "type": "integer"
                }
            }
        },
        "statistics.ProductStatistics": {
            "type": "object",
            "properties": {
                "average_rating": {
                    "type": "number"
                },
                "out_of_stock": {
                    "type": "integer"
                },
                "total_categories": {
                    "type": "integer"
                },
                "total_products": {
                    "type": "integer"
                },
                "total_reviews": {
                    "type": "integer"
                },
                "total_stock": {
                    "type": "integer"
                }
            }
        },
        "statistics.SalesStatistics": {
            "type": "object",
            "properties": {
                "average_order": {
                    "type": "number"
                },
                "cancelled_orders": {
                    "type": "integer"
                },
                "delivered_orders": {
                    "type": "integer"
                },
                "pending_orders": {
                    "type": "integer"
                },
                "shipped_orders": {
                    "type": "integer"
                },
                "total_orders": {
                    "type": "integer"
                },
                "total_revenue": {
                    "type": "number"
                }
            }
        }
    },
    "securityDefinitions": {
        "BearerAuth": {
            "type": "apiKey",
            "name": "Authorization",
            "in": "header"
        }
    }
}